odoo/addons/product_category_tag/README.rst
odoo/addons/product_category_tag/__init__.py
odoo/addons/product_category_tag/__manifest__.py
odoo/addons/product_category_tag/i18n/es.po
odoo/addons/product_category_tag/i18n/it.po
odoo/addons/product_category_tag/i18n/product_category_tag.pot
odoo/addons/product_category_tag/models/__init__.py
odoo/addons/product_category_tag/models/product_category.py
odoo/addons/product_category_tag/models/product_category_tag.py
odoo/addons/product_category_tag/readme/CONTRIBUTORS.md
odoo/addons/product_category_tag/readme/DESCRIPTION.md
odoo/addons/product_category_tag/readme/USAGE.md
odoo/addons/product_category_tag/security/ir.model.access.csv
odoo/addons/product_category_tag/static/description/icon.png
odoo/addons/product_category_tag/static/description/index.html
odoo/addons/product_category_tag/views/product_category_tag_views.xml
odoo/addons/product_category_tag/views/product_category_views.xml
odoo_addon_product_category_tag-18.0.1.0.0.4.dist-info/METADATA
odoo_addon_product_category_tag-18.0.1.0.0.4.dist-info/WHEEL
odoo_addon_product_category_tag-18.0.1.0.0.4.dist-info/top_level.txt
odoo_addon_product_category_tag-18.0.1.0.0.4.dist-info/RECORD
